BinaryOptionsTools/__init__.py
BinaryOptionsTools/api.py
BinaryOptionsTools/bot/__init__.py
BinaryOptionsTools/bot/base.py
BinaryOptionsTools/bot/signals/__init__.py
BinaryOptionsTools/indicators/__init__.py
BinaryOptionsTools/indicators/momentum.py
BinaryOptionsTools/indicators/trend.py
BinaryOptionsTools/platforms/__init__.py
BinaryOptionsTools/platforms/pocketoption/__init__.py
BinaryOptionsTools/platforms/pocketoption/api.py
BinaryOptionsTools/platforms/pocketoption/constants.py
BinaryOptionsTools/platforms/pocketoption/expiration.py
BinaryOptionsTools/platforms/pocketoption/global_value.py
BinaryOptionsTools/platforms/pocketoption/stable_api.py
BinaryOptionsTools/platforms/pocketoption/login/__init__.py
BinaryOptionsTools/platforms/pocketoption/login/test/__init__.py
BinaryOptionsTools/platforms/pocketoption/login/test/login.py
BinaryOptionsTools/platforms/pocketoption/test/__init__.py
BinaryOptionsTools/platforms/pocketoption/test/webdrivertest.py
BinaryOptionsTools/platforms/pocketoption/ws/__init__.py
BinaryOptionsTools/platforms/pocketoption/ws/client.py
BinaryOptionsTools/platforms/pocketoption/ws/channels/__init__.py
BinaryOptionsTools/platforms/pocketoption/ws/channels/base.py
BinaryOptionsTools/platforms/pocketoption/ws/channels/buyv3.py
BinaryOptionsTools/platforms/pocketoption/ws/channels/candles.py
BinaryOptionsTools/platforms/pocketoption/ws/channels/change_symbol.py
BinaryOptionsTools/platforms/pocketoption/ws/channels/get_balances.py
BinaryOptionsTools/platforms/pocketoption/ws/objects/__init__.py
BinaryOptionsTools/platforms/pocketoption/ws/objects/base.py
BinaryOptionsTools/platforms/pocketoption/ws/objects/candles.py
BinaryOptionsTools/platforms/pocketoption/ws/objects/time_sync.py
BinaryOptionsTools/platforms/pocketoption/ws/objects/timesync.py
BinaryOptionsTools/research/__init__.py
BinaryOptionsTools/research/smalowatr.py
BinaryOptionsTools/research/tests/__init__.py
BinaryOptionsTools/research/tests/csv_tests.py
BinaryOptionsTools-1.0.0.dist-info/LICENSE
BinaryOptionsTools-1.0.0.dist-info/METADATA
BinaryOptionsTools-1.0.0.dist-info/WHEEL
BinaryOptionsTools-1.0.0.dist-info/top_level.txt
BinaryOptionsTools-1.0.0.dist-info/RECORD
