Metadata-Version: 2.1
Name: BinaryOptionsTools
Version: 1.0.0
Summary: Tools for Binary Options trading
Home-page: https://github.com/ChipaDevTeam/BinaryOptionsToolsV1
Author: Chipa
Author-email: vigopaul05@gmail.com
License: MIT
Classifier: Programming Language :: Python :: 3
Classifier: License :: OSI Approved :: MIT License
Classifier: Operating System :: OS Independent
Requires-Python: >=3.6
License-File: LICENSE
Requires-Dist: numpy
Requires-Dist: pandas
